<?xml version="1.0" encoding="us-ascii"?>
<gmd:MD_Metadata xmlns:xsi="http://www.w3.org/2001/XMLSchema-instance"
                 xmlns:gco="http://www.isotc211.org/2005/gco"
                 xmlns:gmd="http://www.isotc211.org/2005/gmd"
                 xmlns:srv="http://www.isotc211.org/2005/srv"
                 xmlns:gmx="http://www.isotc211.org/2005/gmx"
                 xmlns:gts="http://www.isotc211.org/2005/gts"
                 xmlns:gsr="http://www.isotc211.org/2005/gsr"
                 xmlns:gmi="http://www.isotc211.org/2005/gmi"
                 xmlns:gml="http://www.opengis.net/gml"
                 xmlns:xlink="http://www.w3.org/1999/xlink">
   <gmd:fileIdentifier>
      <gco:CharacterString>edu.ucar.opensky::articles:10232</gco:CharacterString>
   </gmd:fileIdentifier>
   <gmd:language>
      <gmd:LanguageCode codeList="http://www.loc.gov/standards/iso639-2/"
                        codeListValue="eng; USA"/>
   </gmd:language>
   <gmd:characterSet>
      <gmd:MD_CharacterSetCode codeListValue="utf8"
                               codeList="http://www.isotc211.org/namespace/resources/codeList.xml#MD_CharacterSetCode"/>
   </gmd:characterSet>
   <gmd:hierarchyLevel>
      <gmd:MD_ScopeCode codeList="http://standards.iso.org/ittf/PubliclyAvailableStandards/ISO_19139_Schemas/resources/codelist/ML_gmxCodelists.xml#MD_ScopeCode"
                        codeListValue="document"/>
   </gmd:hierarchyLevel>
   <gmd:contact>
      <gmd:CI_ResponsibleParty>
         <gmd:organisationName>
            <gco:CharacterString>UCAR/NCAR - Library</gco:CharacterString>
         </gmd:organisationName>
         <gmd:positionName>
            <gco:CharacterString>OpenSky Support</gco:CharacterString>
         </gmd:positionName>
         <gmd:contactInfo>
            <gmd:CI_Contact>
               <gmd:address>
                  <gmd:CI_Address>
                     <gmd:deliveryPoint>
                        <gco:CharacterString>PO Box 3000</gco:CharacterString>
                     </gmd:deliveryPoint>
                     <gmd:city>
                        <gco:CharacterString>Boulder</gco:CharacterString>
                     </gmd:city>
                     <gmd:administrativeArea>
                        <gco:CharacterString>CO</gco:CharacterString>
                     </gmd:administrativeArea>
                     <gmd:postalCode>
                        <gco:CharacterString>80307-3000</gco:CharacterString>
                     </gmd:postalCode>
                     <gmd:electronicMailAddress>
                        <gco:CharacterString>opensky@ucar.edu</gco:CharacterString>
                     </gmd:electronicMailAddress>
                  </gmd:CI_Address>
               </gmd:address>
               <gmd:onlineResource>
                  <gmd:CI_OnlineResource>
                     <gmd:linkage>
                        <gmd:URL>http://opensky.ucar.edu/</gmd:URL>
                     </gmd:linkage>
                     <gmd:name>
                        <gco:CharacterString>homepage</gco:CharacterString>
                     </gmd:name>
                  </gmd:CI_OnlineResource>
               </gmd:onlineResource>
            </gmd:CI_Contact>
         </gmd:contactInfo>
         <gmd:role>
            <gmd:CI_RoleCode codeList="codeListLocation#CI_RoleCode" codeListValue="pointOfContact">pointOfContact</gmd:CI_RoleCode>
         </gmd:role>
      </gmd:CI_ResponsibleParty>
   </gmd:contact>
   <gmd:dateStamp>
      <gco:DateTime>2018-11-20T23:35:36.043932</gco:DateTime>
   </gmd:dateStamp>
   <gmd:metadataStandardName>
      <gco:CharacterString>ISO 19115-2 Geographic Information - Metadata - Part 2:
                    Extensions for Imagery and Gridded Data</gco:CharacterString>
   </gmd:metadataStandardName>
   <gmd:metadataStandardVersion>
      <gco:CharacterString>ISO 19115-2:2009(E)</gco:CharacterString>
   </gmd:metadataStandardVersion>
   <gmd:dataSetURI>
      <gco:CharacterString>http://n2t.net/ark:/85065/d7n29xh1</gco:CharacterString>
   </gmd:dataSetURI>
   <gmd:identificationInfo>
      <gmd:MD_DataIdentification>
         <gmd:citation>
            <gmd:CI_Citation>
               <gmd:title>
                  <gco:CharacterString>The Community Climate System Model, version 2</gco:CharacterString>
               </gmd:title>
               <gmd:date>
                  <gmd:CI_Date>
                     <gmd:date>
                        <gco:DateTime>2004-10-01T00:00:00Z</gco:DateTime>
                     </gmd:date>
                     <gmd:dateType>
                        <gmd:CI_DateTypeCode codeList="codeListLocation#CI_DateTypeCode" codeListValue="publication">publication</gmd:CI_DateTypeCode>
                     </gmd:dateType>
                  </gmd:CI_Date>
               </gmd:date>
               <gmd:identifier>
                  <gmd:RS_Identifier>
                     <gmd:code>
                        <gco:CharacterString>http://n2t.net/ark:/85065/d7n29xh1</gco:CharacterString>
                     </gmd:code>
                  </gmd:RS_Identifier>
               </gmd:identifier>
               <gmd:citedResponsibleParty>
                  <gmd:CI_ResponsibleParty>
                     <gmd:individualName>
                        <gco:CharacterString>Kiehl, Jeffrey</gco:CharacterString>
                     </gmd:individualName>
                     <gmd:role>
                        <gmd:CI_RoleCode codeList="codeListLocation#CI_RoleCode" codeListValue="author">author</gmd:CI_RoleCode>
                     </gmd:role>
                  </gmd:CI_ResponsibleParty>
               </gmd:citedResponsibleParty>
               <gmd:citedResponsibleParty>
                  <gmd:CI_ResponsibleParty>
                     <gmd:individualName>
                        <gco:CharacterString>Gent, Peter</gco:CharacterString>
                     </gmd:individualName>
                     <gmd:role>
                        <gmd:CI_RoleCode codeList="codeListLocation#CI_RoleCode" codeListValue="author">author</gmd:CI_RoleCode>
                     </gmd:role>
                  </gmd:CI_ResponsibleParty>
               </gmd:citedResponsibleParty>
               <gmd:citedResponsibleParty>
                  <gmd:CI_ResponsibleParty>
                     <gmd:organisationName>
                        <gco:CharacterString>UCAR/NCAR - Library</gco:CharacterString>
                     </gmd:organisationName>
                     <gmd:role>
                        <gmd:CI_RoleCode codeList="codeListLocation#CI_RoleCode" codeListValue="publisher">publisher</gmd:CI_RoleCode>
                     </gmd:role>
                  </gmd:CI_ResponsibleParty>
               </gmd:citedResponsibleParty>
            </gmd:CI_Citation>
         </gmd:citation>
         <gmd:abstract>
            <gco:CharacterString>The Community Climate System Model, version 2 (CCSM2) is briefly described. A 1000-yr control simulation of the present day climate has been completed without flux adjustments. Minor modifications were made at year 350, which included all five components using the same physical constants. There are very small trends in the upper-ocean, sea ice, atmosphere, and land fields after year 150 of the control simulation. The deep ocean has small but significant trends; however, these are not large enough that the control simulation could not be continued much further. The equilibrium climate sensitivity of CCSM2 is 2.2 K, which is slightly larger than the Climate System Model, version 1 (CSM1) value of 2.0 K. Several aspects of the control simulation's mean climate and interannual variability are described, and good and bad properties of the control simulation are documented. In particular, several aspects of the simulation, especially in the Arctic region, are much improved over those obtained in CSM1. Other aspects, such as the tropical Pacific region simulation, have not been improved much compared to those in CSM1. Priorities for further model development are discussed in the conclusions section.</gco:CharacterString>
         </gmd:abstract>
         <gmd:pointOfContact>
            <gmd:CI_ResponsibleParty>
               <gmd:organisationName>
                  <gco:CharacterString>UCAR/NCAR - Library</gco:CharacterString>
               </gmd:organisationName>
               <gmd:positionName>
                  <gco:CharacterString>OpenSky Support</gco:CharacterString>
               </gmd:positionName>
               <gmd:contactInfo>
                  <gmd:CI_Contact>
                     <gmd:address>
                        <gmd:CI_Address>
                           <gmd:deliveryPoint>
                              <gco:CharacterString>PO Box 3000</gco:CharacterString>
                           </gmd:deliveryPoint>
                           <gmd:city>
                              <gco:CharacterString>Boulder</gco:CharacterString>
                           </gmd:city>
                           <gmd:administrativeArea>
                              <gco:CharacterString>CO</gco:CharacterString>
                           </gmd:administrativeArea>
                           <gmd:postalCode>
                              <gco:CharacterString>80307-3000</gco:CharacterString>
                           </gmd:postalCode>
                           <gmd:electronicMailAddress>
                              <gco:CharacterString>opensky@ucar.edu</gco:CharacterString>
                           </gmd:electronicMailAddress>
                        </gmd:CI_Address>
                     </gmd:address>
                     <gmd:onlineResource>
                        <gmd:CI_OnlineResource>
                           <gmd:linkage>
                              <gmd:URL>http://opensky.ucar.edu/</gmd:URL>
                           </gmd:linkage>
                           <gmd:name>
                              <gco:CharacterString>homepage</gco:CharacterString>
                           </gmd:name>
                        </gmd:CI_OnlineResource>
                     </gmd:onlineResource>
                  </gmd:CI_Contact>
               </gmd:contactInfo>
               <gmd:role>
                  <gmd:CI_RoleCode codeList="codeListLocation#CI_RoleCode" codeListValue="pointOfContact">pointOfContact</gmd:CI_RoleCode>
               </gmd:role>
            </gmd:CI_ResponsibleParty>
         </gmd:pointOfContact>
         <gmd:descriptiveKeywords>
            <gmd:MD_Keywords>
               <gmd:keyword>
                  <gco:CharacterString>Text</gco:CharacterString>
               </gmd:keyword>
               <gmd:type>
                  <gmd:MD_KeywordTypeCode codeList="codeListLocation#MD_KeywordTypeCode" codeListValue="theme">theme</gmd:MD_KeywordTypeCode>
               </gmd:type>
               <gmd:thesaurusName>
                  <gmd:CI_Citation>
                     <gmd:title>
                        <gco:CharacterString>Resource Type</gco:CharacterString>
                     </gmd:title>
                     <gmd:date>
                        <gmd:CI_Date>
                           <gmd:date>
                              <gco:DateTime>2016-01-01T00:00:00Z</gco:DateTime>
                           </gmd:date>
                           <gmd:dateType>
                              <gmd:CI_DateTypeCode codeList="codeListLocation#CI_DateTypeCode" codeListValue="publication">publication</gmd:CI_DateTypeCode>
                           </gmd:dateType>
                        </gmd:CI_Date>
                     </gmd:date>
                  </gmd:CI_Citation>
               </gmd:thesaurusName>
            </gmd:MD_Keywords>
         </gmd:descriptiveKeywords>
         <gmd:resourceConstraints>
            <gmd:MD_LegalConstraints>
               <gmd:useLimitation>
                  <gco:CharacterString>Copyright 2004 American Meteorological Society (AMS). Permission to use figures, tables, and brief excerpts from this work in scientific and educational works is hereby granted provided that the source is acknowledged. Any use of material in this work that is determined to be "fair use" under Section 107 of the U.S. Copyright Act or that satisfies the conditions specified in Section 108 of the U.S. Copyright Act (17 USC &#xa7;108, as revised by P.L. 94-553) does not require the AMS's permission. Republication, systematic reproduction, posting in electronic form on servers, or other uses of this material, except as exempted by the above statement, requires written permission or a license form the AMS. Additional details are provided in the AMS Copyright Policy, available on the AMS Web site located at (http://www.ametsoc.org/AMS) or from the AMS at 617-227-2425 or copyright@ametsoc.org.</gco:CharacterString>
               </gmd:useLimitation>
               <gmd:otherConstraints>
                  <gco:CharacterString>None</gco:CharacterString>
               </gmd:otherConstraints>
            </gmd:MD_LegalConstraints>
         </gmd:resourceConstraints>
         <gmd:language>
            <gmd:LanguageCode codeList="codeListLocation#LanguageCode" codeListValue="eng">eng</gmd:LanguageCode>
         </gmd:language>
         <gmd:topicCategory>
            <gmd:MD_TopicCategoryCode>geoscientificInformation</gmd:MD_TopicCategoryCode>
         </gmd:topicCategory>
      </gmd:MD_DataIdentification>
   </gmd:identificationInfo>
</gmd:MD_Metadata>
