<?xml version="1.0" encoding="UTF-8"?>
<gmd:MD_Metadata xmlns:xsi="http://www.w3.org/2001/XMLSchema-instance"
                 xmlns:gco="http://www.isotc211.org/2005/gco"
                 xmlns:gmd="http://www.isotc211.org/2005/gmd"
                 xmlns:srv="http://www.isotc211.org/2005/srv"
                 xmlns:gmx="http://www.isotc211.org/2005/gmx"
                 xmlns:gts="http://www.isotc211.org/2005/gts"
                 xmlns:gsr="http://www.isotc211.org/2005/gsr"
                 xmlns:gmi="http://www.isotc211.org/2005/gmi"
                 xmlns:gml="http://www.opengis.net/gml"
                 xmlns:xlink="http://www.w3.org/1999/xlink"
                 xsi:schemaLocation="http://www.isotc211.org/2005/gmd http://www.isotc211.org/2005/gmx/gmx.xsd">
   <gmd:fileIdentifier>
      <gco:CharacterString>edu.ucar.opensky::articles:42805</gco:CharacterString>
   </gmd:fileIdentifier>
   <gmd:language>
      <gmd:LanguageCode codeList="http://www.loc.gov/standards/iso639-2/"
                        codeListValue="eng; USA"/>
   </gmd:language>
   <gmd:characterSet>
      <gmd:MD_CharacterSetCode codeListValue="utf8"
                               codeList="http://www.isotc211.org/namespace/resources/codeList.xml#MD_CharacterSetCode"/>
   </gmd:characterSet>
   <gmd:hierarchyLevel>
      <gmd:MD_ScopeCode codeList="http://standards.iso.org/ittf/PubliclyAvailableStandards/ISO_19139_Schemas/resources/codelist/ML_gmxCodelists.xml#MD_ScopeCode"
                        codeListValue="document"/>
   </gmd:hierarchyLevel>
   <gmd:contact>
      <gmd:CI_ResponsibleParty>
         <gmd:organisationName>
            <gco:CharacterString>UCAR/NCAR - Library</gco:CharacterString>
         </gmd:organisationName>
         <gmd:positionName>
            <gco:CharacterString>OpenSky Support</gco:CharacterString>
         </gmd:positionName>
         <gmd:contactInfo>
            <gmd:CI_Contact>
               <gmd:address>
                  <gmd:CI_Address>
                     <gmd:deliveryPoint>
                        <gco:CharacterString>PO Box 3000</gco:CharacterString>
                     </gmd:deliveryPoint>
                     <gmd:city>
                        <gco:CharacterString>Boulder</gco:CharacterString>
                     </gmd:city>
                     <gmd:administrativeArea>
                        <gco:CharacterString>CO</gco:CharacterString>
                     </gmd:administrativeArea>
                     <gmd:postalCode>
                        <gco:CharacterString>80307-3000</gco:CharacterString>
                     </gmd:postalCode>
                     <gmd:electronicMailAddress>
                        <gco:CharacterString>opensky@ucar.edu</gco:CharacterString>
                     </gmd:electronicMailAddress>
                  </gmd:CI_Address>
               </gmd:address>
               <gmd:onlineResource>
                  <gmd:CI_OnlineResource>
                     <gmd:linkage>
                        <gmd:URL>http://opensky.ucar.edu/</gmd:URL>
                     </gmd:linkage>
                     <gmd:name>
                        <gco:CharacterString>homepage</gco:CharacterString>
                     </gmd:name>
                  </gmd:CI_OnlineResource>
               </gmd:onlineResource>
            </gmd:CI_Contact>
         </gmd:contactInfo>
         <gmd:role>
            <gmd:CI_RoleCode codeList="codeListLocation#CI_RoleCode" codeListValue="pointOfContact">pointOfContact</gmd:CI_RoleCode>
         </gmd:role>
      </gmd:CI_ResponsibleParty>
   </gmd:contact>
   <gmd:dateStamp>
      <gco:DateTime>2025-12-24T17:52:26.257014</gco:DateTime>
   </gmd:dateStamp>
   <gmd:metadataStandardName>
      <gco:CharacterString>ISO 19115-2 Geographic Information - Metadata - Part 2:
                    Extensions for Imagery and Gridded Data</gco:CharacterString>
   </gmd:metadataStandardName>
   <gmd:metadataStandardVersion>
      <gco:CharacterString>ISO 19115-2:2009(E)</gco:CharacterString>
   </gmd:metadataStandardVersion>
   <gmd:dataSetURI>
      <gco:CharacterString>https://n2t.net/ark:/85065/d7dn49ck</gco:CharacterString>
   </gmd:dataSetURI>
   <gmd:identificationInfo>
      <gmd:MD_DataIdentification>
         <gmd:citation>
            <gmd:CI_Citation>
               <gmd:title>
                  <gco:CharacterString>Further development and application of the WRFDA-Chem three-dimensional variational (3DVAR) system: Joint assimilation of satellite AOD retrievals and surface observations</gco:CharacterString>
               </gmd:title>
               <gmd:date>
                  <gmd:CI_Date>
                     <gmd:date>
                        <gco:DateTime>2025-04-01T00:00:00Z</gco:DateTime>
                     </gmd:date>
                     <gmd:dateType>
                        <gmd:CI_DateTypeCode codeList="codeListLocation#CI_DateTypeCode" codeListValue="publication">publication</gmd:CI_DateTypeCode>
                     </gmd:dateType>
                  </gmd:CI_Date>
               </gmd:date>
               <gmd:identifier>
                  <gmd:RS_Identifier>
                     <gmd:code>
                        <gco:CharacterString>https://n2t.net/ark:/85065/d7dn49ck</gco:CharacterString>
                     </gmd:code>
                  </gmd:RS_Identifier>
               </gmd:identifier>
               <gmd:identifier>
                  <gmd:RS_Identifier>
                     <gmd:code>
                        <gco:CharacterString>https://doi.org/10.1016/j.atmosres.2025.107942</gco:CharacterString>
                     </gmd:code>
                  </gmd:RS_Identifier>
               </gmd:identifier>
               <gmd:citedResponsibleParty>
                  <gmd:CI_ResponsibleParty>
                     <gmd:individualName>
                        <gco:CharacterString>Zhou, Y.</gco:CharacterString>
                     </gmd:individualName>
                     <gmd:role>
                        <gmd:CI_RoleCode codeList="codeListLocation#CI_RoleCode" codeListValue="author">author</gmd:CI_RoleCode>
                     </gmd:role>
                  </gmd:CI_ResponsibleParty>
               </gmd:citedResponsibleParty>
               <gmd:citedResponsibleParty>
                  <gmd:CI_ResponsibleParty>
                     <gmd:individualName>
                        <gco:CharacterString>Sun, W.</gco:CharacterString>
                     </gmd:individualName>
                     <gmd:role>
                        <gmd:CI_RoleCode codeList="codeListLocation#CI_RoleCode" codeListValue="author">author</gmd:CI_RoleCode>
                     </gmd:role>
                  </gmd:CI_ResponsibleParty>
               </gmd:citedResponsibleParty>
               <gmd:citedResponsibleParty>
                  <gmd:CI_ResponsibleParty>
                     <gmd:individualName>
                        <gmx:Anchor xlink:href="https://orcid.org/0000-0003-4917-7686"
                                    xlink:title="Liu, Zhiquan"
                                    xlink:actuate="onRequest">Liu, Zhiquan</gmx:Anchor>
                     </gmd:individualName>
                     <gmd:role>
                        <gmd:CI_RoleCode codeList="codeListLocation#CI_RoleCode" codeListValue="author">author</gmd:CI_RoleCode>
                     </gmd:role>
                  </gmd:CI_ResponsibleParty>
               </gmd:citedResponsibleParty>
               <gmd:citedResponsibleParty>
                  <gmd:CI_ResponsibleParty>
                     <gmd:individualName>
                        <gco:CharacterString>Gao, L.</gco:CharacterString>
                     </gmd:individualName>
                     <gmd:role>
                        <gmd:CI_RoleCode codeList="codeListLocation#CI_RoleCode" codeListValue="author">author</gmd:CI_RoleCode>
                     </gmd:role>
                  </gmd:CI_ResponsibleParty>
               </gmd:citedResponsibleParty>
               <gmd:citedResponsibleParty>
                  <gmd:CI_ResponsibleParty>
                     <gmd:individualName>
                        <gco:CharacterString>Chen, D.</gco:CharacterString>
                     </gmd:individualName>
                     <gmd:role>
                        <gmd:CI_RoleCode codeList="codeListLocation#CI_RoleCode" codeListValue="author">author</gmd:CI_RoleCode>
                     </gmd:role>
                  </gmd:CI_ResponsibleParty>
               </gmd:citedResponsibleParty>
               <gmd:citedResponsibleParty>
                  <gmd:CI_ResponsibleParty>
                     <gmd:individualName>
                        <gco:CharacterString>Feng, J.</gco:CharacterString>
                     </gmd:individualName>
                     <gmd:role>
                        <gmd:CI_RoleCode codeList="codeListLocation#CI_RoleCode" codeListValue="author">author</gmd:CI_RoleCode>
                     </gmd:role>
                  </gmd:CI_ResponsibleParty>
               </gmd:citedResponsibleParty>
               <gmd:citedResponsibleParty>
                  <gmd:CI_ResponsibleParty>
                     <gmd:individualName>
                        <gco:CharacterString>Zhang, T.</gco:CharacterString>
                     </gmd:individualName>
                     <gmd:role>
                        <gmd:CI_RoleCode codeList="codeListLocation#CI_RoleCode" codeListValue="author">author</gmd:CI_RoleCode>
                     </gmd:role>
                  </gmd:CI_ResponsibleParty>
               </gmd:citedResponsibleParty>
               <gmd:citedResponsibleParty>
                  <gmd:CI_ResponsibleParty>
                     <gmd:individualName>
                        <gco:CharacterString>Zhou, Z.</gco:CharacterString>
                     </gmd:individualName>
                     <gmd:role>
                        <gmd:CI_RoleCode codeList="codeListLocation#CI_RoleCode" codeListValue="author">author</gmd:CI_RoleCode>
                     </gmd:role>
                  </gmd:CI_ResponsibleParty>
               </gmd:citedResponsibleParty>
               <gmd:citedResponsibleParty>
                  <gmd:CI_ResponsibleParty>
                     <gmd:organisationName>
                        <gco:CharacterString>UCAR/NCAR - Library</gco:CharacterString>
                     </gmd:organisationName>
                     <gmd:role>
                        <gmd:CI_RoleCode codeList="codeListLocation#CI_RoleCode" codeListValue="publisher">publisher</gmd:CI_RoleCode>
                     </gmd:role>
                  </gmd:CI_ResponsibleParty>
               </gmd:citedResponsibleParty>
            </gmd:CI_Citation>
         </gmd:citation>
         <gmd:abstract>
            <gco:CharacterString>&lt;p&gt;&lt;span style="-webkit-text-stroke-width:0px;color:rgb(31, 31, 31);display:inline !important;float:none;font-family:ElsevierGulliver, Georgia, &amp;quot;Times New Roman&amp;quot;, Times, STIXGeneral, &amp;quot;Cambria Math&amp;quot;, &amp;quot;Lucida Sans Unicode&amp;quot;, &amp;quot;Microsoft Sans Serif&amp;quot;, &amp;quot;Segoe UI Symbol&amp;quot;, &amp;quot;Arial Unicode MS&amp;quot;, serif, sans-serif;font-size:16px;font-style:normal;font-variant-caps:normal;font-variant-ligatures:normal;font-weight:400;letter-spacing:normal;orphans:2;text-align:start;text-decoration-color:initial;text-decoration-style:initial;text-decoration-thickness:initial;text-indent:0px;text-transform:none;white-space:normal;widows:2;word-spacing:0px;"&gt;The capability to assimilate Aerosol Optical Depth (AOD) is developed within the WRFDA system in this study using the three-dimensional variational (3DVar) algorithm, based on the Model for Simulating Aerosol Interactions and Chemistry (MOSAIC) aerosol scheme of the Weather Research and Forecasting model coupled with online Chemistry (WRF-Chem). Experiments assimilating Himawari-8 satellite AOD retrievals along with surface observations (PM&lt;/span&gt;&lt;sub style="-webkit-text-stroke-width:0px;bottom:-0.25em;box-sizing:border-box;color:rgb(31, 31, 31);font-family:ElsevierGulliver, Georgia, &amp;quot;Times New Roman&amp;quot;, Times, STIXGeneral, &amp;quot;Cambria Math&amp;quot;, &amp;quot;Lucida Sans Unicode&amp;quot;, &amp;quot;Microsoft Sans Serif&amp;quot;, &amp;quot;Segoe UI Symbol&amp;quot;, &amp;quot;Arial Unicode MS&amp;quot;, serif, sans-serif;font-size:12px;font-style:normal;font-variant-caps:normal;font-variant-ligatures:normal;font-weight:400;letter-spacing:normal;line-height:0;margin:0px;orphans:2;padding:0px;position:relative;text-align:start;text-decoration-color:initial;text-decoration-style:initial;text-decoration-thickness:initial;text-indent:0px;text-transform:none;vertical-align:baseline;white-space:normal;widows:2;word-spacing:0px;"&gt;2.5,&lt;/sub&gt;&lt;span style="-webkit-text-stroke-width:0px;color:rgb(31, 31, 31);display:inline !important;float:none;font-family:ElsevierGulliver, Georgia, &amp;quot;Times New Roman&amp;quot;, Times, STIXGeneral, &amp;quot;Cambria Math&amp;quot;, &amp;quot;Lucida Sans Unicode&amp;quot;, &amp;quot;Microsoft Sans Serif&amp;quot;, &amp;quot;Segoe UI Symbol&amp;quot;, &amp;quot;Arial Unicode MS&amp;quot;, serif, sans-serif;font-size:16px;font-style:normal;font-variant-caps:normal;font-variant-ligatures:normal;font-weight:400;letter-spacing:normal;orphans:2;text-align:start;text-decoration-color:initial;text-decoration-style:initial;text-decoration-thickness:initial;text-indent:0px;text-transform:none;white-space:normal;widows:2;word-spacing:0px;"&gt; PM&lt;/span&gt;&lt;sub style="-webkit-text-stroke-width:0px;bottom:-0.25em;box-sizing:border-box;color:rgb(31, 31, 31);font-family:ElsevierGulliver, Georgia, &amp;quot;Times New Roman&amp;quot;, Times, STIXGeneral, &amp;quot;Cambria Math&amp;quot;, &amp;quot;Lucida Sans Unicode&amp;quot;, &amp;quot;Microsoft Sans Serif&amp;quot;, &amp;quot;Segoe UI Symbol&amp;quot;, &amp;quot;Arial Unicode MS&amp;quot;, serif, sans-serif;font-size:12px;font-style:normal;font-variant-caps:normal;font-variant-ligatures:normal;font-weight:400;letter-spacing:normal;line-height:0;margin:0px;orphans:2;padding:0px;position:relative;text-align:start;text-decoration-color:initial;text-decoration-style:initial;text-decoration-thickness:initial;text-indent:0px;text-transform:none;vertical-align:baseline;white-space:normal;widows:2;word-spacing:0px;"&gt;10&lt;/sub&gt;&lt;span style="-webkit-text-stroke-width:0px;color:rgb(31, 31, 31);display:inline !important;float:none;font-family:ElsevierGulliver, Georgia, &amp;quot;Times New Roman&amp;quot;, Times, STIXGeneral, &amp;quot;Cambria Math&amp;quot;, &amp;quot;Lucida Sans Unicode&amp;quot;, &amp;quot;Microsoft Sans Serif&amp;quot;, &amp;quot;Segoe UI Symbol&amp;quot;, &amp;quot;Arial Unicode MS&amp;quot;, serif, sans-serif;font-size:16px;font-style:normal;font-variant-caps:normal;font-variant-ligatures:normal;font-weight:400;letter-spacing:normal;orphans:2;text-align:start;text-decoration-color:initial;text-decoration-style:initial;text-decoration-thickness:initial;text-indent:0px;text-transform:none;white-space:normal;widows:2;word-spacing:0px;"&gt;, SO&lt;/span&gt;&lt;sub style="-webkit-text-stroke-width:0px;bottom:-0.25em;box-sizing:border-box;color:rgb(31, 31, 31);font-family:ElsevierGulliver, Georgia, &amp;quot;Times New Roman&amp;quot;, Times, STIXGeneral, &amp;quot;Cambria Math&amp;quot;, &amp;quot;Lucida Sans Unicode&amp;quot;, &amp;quot;Microsoft Sans Serif&amp;quot;, &amp;quot;Segoe UI Symbol&amp;quot;, &amp;quot;Arial Unicode MS&amp;quot;, serif, sans-serif;font-size:12px;font-style:normal;font-variant-caps:normal;font-variant-ligatures:normal;font-weight:400;letter-spacing:normal;line-height:0;margin:0px;orphans:2;padding:0px;position:relative;text-align:start;text-decoration-color:initial;text-decoration-style:initial;text-decoration-thickness:initial;text-indent:0px;text-transform:none;vertical-align:baseline;white-space:normal;widows:2;word-spacing:0px;"&gt;2&lt;/sub&gt;&lt;span style="-webkit-text-stroke-width:0px;color:rgb(31, 31, 31);display:inline !important;float:none;font-family:ElsevierGulliver, Georgia, &amp;quot;Times New Roman&amp;quot;, Times, STIXGeneral, &amp;quot;Cambria Math&amp;quot;, &amp;quot;Lucida Sans Unicode&amp;quot;, &amp;quot;Microsoft Sans Serif&amp;quot;, &amp;quot;Segoe UI Symbol&amp;quot;, &amp;quot;Arial Unicode MS&amp;quot;, serif, sans-serif;font-size:16px;font-style:normal;font-variant-caps:normal;font-variant-ligatures:normal;font-weight:400;letter-spacing:normal;orphans:2;text-align:start;text-decoration-color:initial;text-decoration-style:initial;text-decoration-thickness:initial;text-indent:0px;text-transform:none;white-space:normal;widows:2;word-spacing:0px;"&gt;, NO&lt;/span&gt;&lt;sub style="-webkit-text-stroke-width:0px;bottom:-0.25em;box-sizing:border-box;color:rgb(31, 31, 31);font-family:ElsevierGulliver, Georgia, &amp;quot;Times New Roman&amp;quot;, Times, STIXGeneral, &amp;quot;Cambria Math&amp;quot;, &amp;quot;Lucida Sans Unicode&amp;quot;, &amp;quot;Microsoft Sans Serif&amp;quot;, &amp;quot;Segoe UI Symbol&amp;quot;, &amp;quot;Arial Unicode MS&amp;quot;, serif, sans-serif;font-size:12px;font-style:normal;font-variant-caps:normal;font-variant-ligatures:normal;font-weight:400;letter-spacing:normal;line-height:0;margin:0px;orphans:2;padding:0px;position:relative;text-align:start;text-decoration-color:initial;text-decoration-style:initial;text-decoration-thickness:initial;text-indent:0px;text-transform:none;vertical-align:baseline;white-space:normal;widows:2;word-spacing:0px;"&gt;2&lt;/sub&gt;&lt;span style="-webkit-text-stroke-width:0px;color:rgb(31, 31, 31);display:inline !important;float:none;font-family:ElsevierGulliver, Georgia, &amp;quot;Times New Roman&amp;quot;, Times, STIXGeneral, &amp;quot;Cambria Math&amp;quot;, &amp;quot;Lucida Sans Unicode&amp;quot;, &amp;quot;Microsoft Sans Serif&amp;quot;, &amp;quot;Segoe UI Symbol&amp;quot;, &amp;quot;Arial Unicode MS&amp;quot;, serif, sans-serif;font-size:16px;font-style:normal;font-variant-caps:normal;font-variant-ligatures:normal;font-weight:400;letter-spacing:normal;orphans:2;text-align:start;text-decoration-color:initial;text-decoration-style:initial;text-decoration-thickness:initial;text-indent:0px;text-transform:none;white-space:normal;widows:2;word-spacing:0px;"&gt;, O&lt;/span&gt;&lt;sub style="-webkit-text-stroke-width:0px;bottom:-0.25em;box-sizing:border-box;color:rgb(31, 31, 31);font-family:ElsevierGulliver, Georgia, &amp;quot;Times New Roman&amp;quot;, Times, STIXGeneral, &amp;quot;Cambria Math&amp;quot;, &amp;quot;Lucida Sans Unicode&amp;quot;, &amp;quot;Microsoft Sans Serif&amp;quot;, &amp;quot;Segoe UI Symbol&amp;quot;, &amp;quot;Arial Unicode MS&amp;quot;, serif, sans-serif;font-size:12px;font-style:normal;font-variant-caps:normal;font-variant-ligatures:normal;font-weight:400;letter-spacing:normal;line-height:0;margin:0px;orphans:2;padding:0px;position:relative;text-align:start;text-decoration-color:initial;text-decoration-style:initial;text-decoration-thickness:initial;text-indent:0px;text-transform:none;vertical-align:baseline;white-space:normal;widows:2;word-spacing:0px;"&gt;3&lt;/sub&gt;&lt;span style="-webkit-text-stroke-width:0px;color:rgb(31, 31, 31);display:inline !important;float:none;font-family:ElsevierGulliver, Georgia, &amp;quot;Times New Roman&amp;quot;, Times, STIXGeneral, &amp;quot;Cambria Math&amp;quot;, &amp;quot;Lucida Sans Unicode&amp;quot;, &amp;quot;Microsoft Sans Serif&amp;quot;, &amp;quot;Segoe UI Symbol&amp;quot;, &amp;quot;Arial Unicode MS&amp;quot;, serif, sans-serif;font-size:16px;font-style:normal;font-variant-caps:normal;font-variant-ligatures:normal;font-weight:400;letter-spacing:normal;orphans:2;text-align:start;text-decoration-color:initial;text-decoration-style:initial;text-decoration-thickness:initial;text-indent:0px;text-transform:none;white-space:normal;widows:2;word-spacing:0px;"&gt;, and CO) are conducted over China for the period from 25 December 2016 to 9 January 2017. The performances of data assimilation for both analyses and forecasts are evaluated against various datasets, including the surface PM&lt;/span&gt;&lt;sub style="-webkit-text-stroke-width:0px;bottom:-0.25em;box-sizing:border-box;color:rgb(31, 31, 31);font-family:ElsevierGulliver, Georgia, &amp;quot;Times New Roman&amp;quot;, Times, STIXGeneral, &amp;quot;Cambria Math&amp;quot;, &amp;quot;Lucida Sans Unicode&amp;quot;, &amp;quot;Microsoft Sans Serif&amp;quot;, &amp;quot;Segoe UI Symbol&amp;quot;, &amp;quot;Arial Unicode MS&amp;quot;, serif, sans-serif;font-size:12px;font-style:normal;font-variant-caps:normal;font-variant-ligatures:normal;font-weight:400;letter-spacing:normal;line-height:0;margin:0px;orphans:2;padding:0px;position:relative;text-align:start;text-decoration-color:initial;text-decoration-style:initial;text-decoration-thickness:initial;text-indent:0px;text-transform:none;vertical-align:baseline;white-space:normal;widows:2;word-spacing:0px;"&gt;2.5&lt;/sub&gt;&lt;span style="-webkit-text-stroke-width:0px;color:rgb(31, 31, 31);display:inline !important;float:none;font-family:ElsevierGulliver, Georgia, &amp;quot;Times New Roman&amp;quot;, Times, STIXGeneral, &amp;quot;Cambria Math&amp;quot;, &amp;quot;Lucida Sans Unicode&amp;quot;, &amp;quot;Microsoft Sans Serif&amp;quot;, &amp;quot;Segoe UI Symbol&amp;quot;, &amp;quot;Arial Unicode MS&amp;quot;, serif, sans-serif;font-size:16px;font-style:normal;font-variant-caps:normal;font-variant-ligatures:normal;font-weight:400;letter-spacing:normal;orphans:2;text-align:start;text-decoration-color:initial;text-decoration-style:initial;text-decoration-thickness:initial;text-indent:0px;text-transform:none;white-space:normal;widows:2;word-spacing:0px;"&gt; and PM&lt;/span&gt;&lt;sub style="-webkit-text-stroke-width:0px;bottom:-0.25em;box-sizing:border-box;color:rgb(31, 31, 31);font-family:ElsevierGulliver, Georgia, &amp;quot;Times New Roman&amp;quot;, Times, STIXGeneral, &amp;quot;Cambria Math&amp;quot;, &amp;quot;Lucida Sans Unicode&amp;quot;, &amp;quot;Microsoft Sans Serif&amp;quot;, &amp;quot;Segoe UI Symbol&amp;quot;, &amp;quot;Arial Unicode MS&amp;quot;, serif, sans-serif;font-size:12px;font-style:normal;font-variant-caps:normal;font-variant-ligatures:normal;font-weight:400;letter-spacing:normal;line-height:0;margin:0px;orphans:2;padding:0px;position:relative;text-align:start;text-decoration-color:initial;text-decoration-style:initial;text-decoration-thickness:initial;text-indent:0px;text-transform:none;vertical-align:baseline;white-space:normal;widows:2;word-spacing:0px;"&gt;10&lt;/sub&gt;&lt;span style="-webkit-text-stroke-width:0px;color:rgb(31, 31, 31);display:inline !important;float:none;font-family:ElsevierGulliver, Georgia, &amp;quot;Times New Roman&amp;quot;, Times, STIXGeneral, &amp;quot;Cambria Math&amp;quot;, &amp;quot;Lucida Sans Unicode&amp;quot;, &amp;quot;Microsoft Sans Serif&amp;quot;, &amp;quot;Segoe UI Symbol&amp;quot;, &amp;quot;Arial Unicode MS&amp;quot;, serif, sans-serif;font-size:16px;font-style:normal;font-variant-caps:normal;font-variant-ligatures:normal;font-weight:400;letter-spacing:normal;orphans:2;text-align:start;text-decoration-color:initial;text-decoration-style:initial;text-decoration-thickness:initial;text-indent:0px;text-transform:none;white-space:normal;widows:2;word-spacing:0px;"&gt; measurements, the Himawari-8 AOD and aerosol extinction coefficient (AEC) profile data from the Cloud-Aerosol Lidar and Infrared Pathfinder Satellite Observations (CALIPSO). The DA experiments exhibit positive effects on the analyses and forecasts of surface PM&lt;/span&gt;&lt;sub style="-webkit-text-stroke-width:0px;bottom:-0.25em;box-sizing:border-box;color:rgb(31, 31, 31);font-family:ElsevierGulliver, Georgia, &amp;quot;Times New Roman&amp;quot;, Times, STIXGeneral, &amp;quot;Cambria Math&amp;quot;, &amp;quot;Lucida Sans Unicode&amp;quot;, &amp;quot;Microsoft Sans Serif&amp;quot;, &amp;quot;Segoe UI Symbol&amp;quot;, &amp;quot;Arial Unicode MS&amp;quot;, serif, sans-serif;font-size:12px;font-style:normal;font-variant-caps:normal;font-variant-ligatures:normal;font-weight:400;letter-spacing:normal;line-height:0;margin:0px;orphans:2;padding:0px;position:relative;text-align:start;text-decoration-color:initial;text-decoration-style:initial;text-decoration-thickness:initial;text-indent:0px;text-transform:none;vertical-align:baseline;white-space:normal;widows:2;word-spacing:0px;"&gt;2.5&lt;/sub&gt;&lt;span style="-webkit-text-stroke-width:0px;color:rgb(31, 31, 31);display:inline !important;float:none;font-family:ElsevierGulliver, Georgia, &amp;quot;Times New Roman&amp;quot;, Times, STIXGeneral, &amp;quot;Cambria Math&amp;quot;, &amp;quot;Lucida Sans Unicode&amp;quot;, &amp;quot;Microsoft Sans Serif&amp;quot;, &amp;quot;Segoe UI Symbol&amp;quot;, &amp;quot;Arial Unicode MS&amp;quot;, serif, sans-serif;font-size:16px;font-style:normal;font-variant-caps:normal;font-variant-ligatures:normal;font-weight:400;letter-spacing:normal;orphans:2;text-align:start;text-decoration-color:initial;text-decoration-style:initial;text-decoration-thickness:initial;text-indent:0px;text-transform:none;white-space:normal;widows:2;word-spacing:0px;"&gt; and PM&lt;/span&gt;&lt;sub style="-webkit-text-stroke-width:0px;bottom:-0.25em;box-sizing:border-box;color:rgb(31, 31, 31);font-family:ElsevierGulliver, Georgia, &amp;quot;Times New Roman&amp;quot;, Times, STIXGeneral, &amp;quot;Cambria Math&amp;quot;, &amp;quot;Lucida Sans Unicode&amp;quot;, &amp;quot;Microsoft Sans Serif&amp;quot;, &amp;quot;Segoe UI Symbol&amp;quot;, &amp;quot;Arial Unicode MS&amp;quot;, serif, sans-serif;font-size:12px;font-style:normal;font-variant-caps:normal;font-variant-ligatures:normal;font-weight:400;letter-spacing:normal;line-height:0;margin:0px;orphans:2;padding:0px;position:relative;text-align:start;text-decoration-color:initial;text-decoration-style:initial;text-decoration-thickness:initial;text-indent:0px;text-transform:none;vertical-align:baseline;white-space:normal;widows:2;word-spacing:0px;"&gt;10&lt;/sub&gt;&lt;span style="-webkit-text-stroke-width:0px;color:rgb(31, 31, 31);display:inline !important;float:none;font-family:ElsevierGulliver, Georgia, &amp;quot;Times New Roman&amp;quot;, Times, STIXGeneral, &amp;quot;Cambria Math&amp;quot;, &amp;quot;Lucida Sans Unicode&amp;quot;, &amp;quot;Microsoft Sans Serif&amp;quot;, &amp;quot;Segoe UI Symbol&amp;quot;, &amp;quot;Arial Unicode MS&amp;quot;, serif, sans-serif;font-size:16px;font-style:normal;font-variant-caps:normal;font-variant-ligatures:normal;font-weight:400;letter-spacing:normal;orphans:2;text-align:start;text-decoration-color:initial;text-decoration-style:initial;text-decoration-thickness:initial;text-indent:0px;text-transform:none;white-space:normal;widows:2;word-spacing:0px;"&gt;, AOD, and aerosol vertical extinction coefficient to different degrees. Compared to the assimilation of ground-based observations, which is highly effective in improving surface aerosol forecasts, the Himawari-8 AOD assimilation exhibits a greater improvement on the AOD and AEC profile. The experiment assimilating the Himawari-8 AOD and surface observations simultaneously performs the best, in terms of both the horizontal and vertical distributions of aerosols. Results reveal the potential of the combined assimilation of satellite retrievals and surface observations, especially in generating a better aerosol structure for both analyses and forecasts.&lt;/span&gt;&lt;/p&gt;</gco:CharacterString>
         </gmd:abstract>
         <gmd:pointOfContact>
            <gmd:CI_ResponsibleParty>
               <gmd:organisationName>
                  <gco:CharacterString>UCAR/NCAR - Library</gco:CharacterString>
               </gmd:organisationName>
               <gmd:positionName>
                  <gco:CharacterString>OpenSky Support</gco:CharacterString>
               </gmd:positionName>
               <gmd:contactInfo>
                  <gmd:CI_Contact>
                     <gmd:address>
                        <gmd:CI_Address>
                           <gmd:deliveryPoint>
                              <gco:CharacterString>PO Box 3000</gco:CharacterString>
                           </gmd:deliveryPoint>
                           <gmd:city>
                              <gco:CharacterString>Boulder</gco:CharacterString>
                           </gmd:city>
                           <gmd:administrativeArea>
                              <gco:CharacterString>CO</gco:CharacterString>
                           </gmd:administrativeArea>
                           <gmd:postalCode>
                              <gco:CharacterString>80307-3000</gco:CharacterString>
                           </gmd:postalCode>
                           <gmd:electronicMailAddress>
                              <gco:CharacterString>opensky@ucar.edu</gco:CharacterString>
                           </gmd:electronicMailAddress>
                        </gmd:CI_Address>
                     </gmd:address>
                     <gmd:onlineResource>
                        <gmd:CI_OnlineResource>
                           <gmd:linkage>
                              <gmd:URL>http://opensky.ucar.edu/</gmd:URL>
                           </gmd:linkage>
                           <gmd:name>
                              <gco:CharacterString>homepage</gco:CharacterString>
                           </gmd:name>
                        </gmd:CI_OnlineResource>
                     </gmd:onlineResource>
                  </gmd:CI_Contact>
               </gmd:contactInfo>
               <gmd:role>
                  <gmd:CI_RoleCode codeList="codeListLocation#CI_RoleCode" codeListValue="pointOfContact">pointOfContact</gmd:CI_RoleCode>
               </gmd:role>
            </gmd:CI_ResponsibleParty>
         </gmd:pointOfContact>
         <gmd:resourceFormat>
            <gmd:MD_Format>
               <gmd:name>
                  <gco:CharacterString>PDF</gco:CharacterString>
               </gmd:name>
               <gmd:version/>
            </gmd:MD_Format>
         </gmd:resourceFormat>
         <gmd:descriptiveKeywords>
            <gmd:MD_Keywords>
               <gmd:keyword>
                  <gco:CharacterString>Text</gco:CharacterString>
               </gmd:keyword>
               <gmd:type>
                  <gmd:MD_KeywordTypeCode codeList="codeListLocation#MD_KeywordTypeCode" codeListValue="theme">theme</gmd:MD_KeywordTypeCode>
               </gmd:type>
               <gmd:thesaurusName>
                  <gmd:CI_Citation>
                     <gmd:title>
                        <gco:CharacterString>Resource Type</gco:CharacterString>
                     </gmd:title>
                     <gmd:date>
                        <gmd:CI_Date>
                           <gmd:date>
                              <gco:DateTime>2016-01-01T00:00:00Z</gco:DateTime>
                           </gmd:date>
                           <gmd:dateType>
                              <gmd:CI_DateTypeCode codeList="codeListLocation#CI_DateTypeCode" codeListValue="publication">publication</gmd:CI_DateTypeCode>
                           </gmd:dateType>
                        </gmd:CI_Date>
                     </gmd:date>
                  </gmd:CI_Citation>
               </gmd:thesaurusName>
            </gmd:MD_Keywords>
         </gmd:descriptiveKeywords>
         <gmd:resourceConstraints>
            <gmd:MD_LegalConstraints>
               <gmd:useLimitation>
                  <gco:CharacterString>&lt;span style="font-family:Arial;font-size:10pt;font-style:normal;" data-sheets-root="1"&gt;Copyright author(s). This work is licensed under a Creative Commons Attribution-NonCommercial 4.0 International License.&lt;/span&gt;</gco:CharacterString>
               </gmd:useLimitation>
               <gmd:otherConstraints>
                  <gco:CharacterString>None</gco:CharacterString>
               </gmd:otherConstraints>
            </gmd:MD_LegalConstraints>
         </gmd:resourceConstraints>
         <gmd:language>
            <gmd:LanguageCode codeList="codeListLocation#LanguageCode" codeListValue="eng">eng</gmd:LanguageCode>
         </gmd:language>
         <gmd:topicCategory>
            <gmd:MD_TopicCategoryCode>geoscientificInformation</gmd:MD_TopicCategoryCode>
         </gmd:topicCategory>
      </gmd:MD_DataIdentification>
   </gmd:identificationInfo>
</gmd:MD_Metadata>
